AUTHORS.txt
CHANGELOG
LICENSE.txt
MANIFEST.in
Makefile
README.rst
setup.cfg
setup.py
gitbuster/__init__.py
gitbuster/branch_name_dialog.py
gitbuster/branch_name_dialog_ui.py
gitbuster/branch_view_ui.py
gitbuster/confirm_dialog.py
gitbuster/confirm_dialog_ui.py
gitbuster/conflicts_dialog.py
gitbuster/conflicts_dialog_ui.py
gitbuster/filter_main_class.py
gitbuster/gitbuster
gitbuster/gitbuster_rc.py
gitbuster/graphics_items.py
gitbuster/main_window.py
gitbuster/main_window_ui.py
gitbuster/progress_thread.py
gitbuster/q_editable_git_model.py
gitbuster/q_git_delegate.py
gitbuster/q_git_model.py
gitbuster/rebase_main_class.py
gitbuster/remote_branch_dialog.py
gitbuster/remote_branch_dialog_ui.py
gitbuster/test_ui.py
gitbuster/util.py
gitbuster.egg-info/PKG-INFO
gitbuster.egg-info/SOURCES.txt
gitbuster.egg-info/dependency_links.txt
gitbuster.egg-info/requires.txt
gitbuster.egg-info/top_level.txt