Metadata-Version: 1.0
Name: gitbuster
Version: 2.0.0b1
Summary: Python Qt4 frontend for git filter-branch and git cherry-pick.
Home-page: https://github.com/mike-perdide/gitbuster
Author: Julien Miotte
Author-email: miotte.julien@gmail.com
License: GPLv3
Keywords: git,frontend,change dates,rewrite history,rebase,cherry-pick
Platform: UNKNOWN
Classifier: Development Status :: 3 - Alpha
Classifier: License :: OSI Approved :: GNU General Public License (GPL)
Classifier: Environment :: X11 Applications :: Qt
Classifier: Intended Audience :: Developers
Classifier: Operating System :: POSIX :: Linux
Classifier: Programming Language :: Python :: 2.6
Classifier: Topic :: Software Development :: Version Control
